fbi_wanted_analysis/__init__.py
fbi_wanted_analysis/analysis.py
fbi_wanted_analysis/cleaning.py
fbi_wanted_analysis/rewards.py
fbi_wanted_analysis/streamlit_app.py
fbi_wanted_analysis-0.2.0.dist-info/WHEEL
fbi_wanted_analysis-0.2.0.dist-info/METADATA
fbi_wanted_analysis-0.2.0.dist-info/RECORD
