Metadata-Version: 2.3
Name: fbi-wanted-analysis
Version: 0.2.0
Summary: STAT 386 project: analysis of FBI Wanted listings using the FBI Wanted API.
Author: Dallin Robinson, Michael Stutzman
License: MIT License
Classifier: License :: OSI Approved :: MIT License
Classifier: Programming Language :: Python :: 3
Classifier: Operating System :: OS Independent
Requires-Dist: ipykernel>=7.1.0
Requires-Dist: jupyter>=1.1.1
Requires-Dist: matplotlib>=3.10.8
Requires-Dist: numpy>=2.3.5
Requires-Dist: pandas>=2.3.3
Requires-Dist: streamlit>=1.40.0
Requires-Python: >=3.11
